pyexifinfo/__init__.py
pyexifinfo/pyexifinfo.py
pyexifinfo_ivc-0.4.2.dist-info/METADATA
pyexifinfo_ivc-0.4.2.dist-info/RECORD
pyexifinfo_ivc-0.4.2.dist-info/WHEEL
pyexifinfo_ivc-0.4.2.dist-info/top_level.txt
