Metadata-Version: 2.1
Name: pyexifinfo-ivc
Version: 0.4.2
Summary: Simple Metadata extraction using Exiftool
Home-page: https://github.com/ivc-inform/pyexifinfo.git
Author: Guinslym
Author-email: guinslym@gmail.com
License: GNU GPLv2
Keywords: exiftool reader stats metadata image linux
Platform: UNKNOWN
Classifier: Development Status :: 5 - Production/Stable
Classifier: Intended Audience :: Developers
Classifier: License :: OSI Approved :: GNU General Public License v3 or later (GPLv3+)
Classifier: Programming Language :: Python :: 2
Classifier: Programming Language :: Python :: 2.6
Classifier: Programming Language :: Python :: 2.7
Classifier: Programming Language :: Python :: 3
Classifier: Programming Language :: Python :: 3.2
Classifier: Programming Language :: Python :: 3.3
Classifier: Programming Language :: Python :: 3.4
Classifier: Topic :: Internet :: WWW/HTTP :: Indexing/Search
